{
  "#source": [
    "http://calendar.ut.ac.ir/Fa/Tyear/Data%5Choliday-1394.pdf",
    "http://pcci.ir/file/2015/11/1395.zip",
    "https://calendar.ut.ac.ir/Fa/News/Data/Doc/calendar%201396-full.pdf",
    "https://calendar.ut.ac.ir/Fa/News/Data/Doc/Calendar%201397-Full.pdf",
    "https://www.tasnimnews.com/fa/news/1395/11/10/1310977/",

    "https://raw.githubusercontent.com/ilius/starcal/master/plugins/iran-jalali-data.txt",
    "مطابق با استخراج و تنظیم شورای مرکز تقویم مؤسسهٔ ژئوفیزیک دانشگاه تهران(مناسبت‌ها از شورای فرهنگ عمومی)",
    "گردآوری، فرمت‌بندی و به روزآوری: سعید رسولی <saeed.gnu@gmail.com>، مولا پهنادایان <mola.mp@gmail.com>",

    "https://raw.githubusercontent.com/ilius/starcal/master/plugins/iran-jalali-2-data.txt",
    "شورای مرکز تقویم مؤسسهٔ ژئوفیزیک دانشگاه تهران، و شورای فرهنگ عمومی",
    "سعید رسولی <saeed.gnu@gmail.com> مولا پهنادایان <mola.mp@gmail.com>",

    "https://raw.githubusercontent.com/ilius/starcal/master/plugins/iran-ancient-data.txt",
    "جشن‌های باستانی ایران",
    "رضا مرادی قیاس آبادی (www.ghiasabadi.com) سعید رسولی <saeed.gnu@gmail.com>",

    "https://raw.githubusercontent.com/ilius/starcal/master/plugins/iran-gregorian-data.txt",
    "https://raw.githubusercontent.com/ilius/starcal/master/plugins/iran-gregorian-2-data.txt",
    "https://raw.githubusercontent.com/ilius/starcal/master/plugins/iran-hijri-data.txt",
    "https://raw.githubusercontent.com/ilius/starcal/master/plugins/iran-hijri-2-data.txt",
    "شورای مرکز تقویم مؤسسهٔ ژئوفیزیک دانشگاه تهران، و شورای فرهنگ عمومی",
    "سعید رسولی <saeed.gnu@gmail.com> مولا پهنادایان <mola.mp@gmail.com>",

    "Afghanistan events from Afghani app clones and https://en.wikipedia.org/wiki/Public_holidays_in_Afghanistan"
  ],
  "global_gregorian_events": [
    { "month": 3, "day": 22, "title": "روز جهانی آب" },
    { "month": 3, "day": 23, "title": "روز جهانی هواشناسی" },
    { "month": 5, "day": 5, "title": "روز جهانی ماما" },
    { "month": 5, "day": 8, "title": "روز جهانی صلیب سرخ و هلال احمر" },
    { "month": 5, "day": 18, "title": "روز جهانی موزه و میراث فرهنگی" },
    { "month": 5, "day": 31, "title": "روز جهانی بدون دخانیات" },
    { "month": 6, "day": 10, "title": "روز جهانی صنایع دستی" },
    { "month": 6, "day": 17, "title": "روز جهانی بیابان‌زدایی" },
    { "month": 6, "day": 26, "title": "روز جهانی مبارزه با مواد مخدر" },
    { "month": 8, "day": 1, "title": "روز جهانی شیر مادر" },
    { "month": 8, "day": 6, "title": "انفجار بمب اتمی آمریکا در هیروشیما با بیش از ۱۶۰ هزار کشته و مجروح (۱۹۴۵ میلادی)" },
    { "month": 9, "day": 27, "title": "روز جهانی جهانگردی" },
    { "month": 9, "day": 30, "title": "روز جهانی ناشنوایان – روز جهانی دریانوردی" },
    { "month": 10, "day": 1, "title": "روز جهانی سالمندان" },
    { "month": 10, "day": 8, "title": "روز جهانی کودک" },
    { "month": 10, "day": 9, "title": "روز جهانی پست" },
    { "month": 10, "day": 14, "title": "روز جهانی استاندارد" },
    { "month": 10, "day": 16, "title": "روز جهانی غذا" },
    { "month": 12, "day": 1, "title": "روز جهانی مبارزه با ایدز" },
    { "month": 12, "day": 7, "title": "روز جهانی هواپیمایی" },
    { "month": 1, "day": 1, "title": "آغاز سال میلادی" },
    { "month": 5, "day": 1, "title": "روز جهانی کار و کارگر" },
    { "month": 6, "day": 5, "title": "روز جهانی محیط زیست" },
    { "month": 8, "day": 21, "title": "روز جهانی مسجد" },
    { "month": 10, "day": 15, "title": "روز جهانی نابینایان (عصای سفید)" },
    { "month": 11, "day": 10, "title": "روز جهانی علم در خدمت صلح و توسعه" },
    { "month": 12, "day": 3, "title": "روز جهانی معلولان" },
    { "month": 12, "day": 18, "title": "روز جهان عاری از خشونت و افراطی‌گری" },
    { "month": 12, "day": 25, "title": "ولادت حضرت عیسی مسیح (ع)" }
  ],
  "afghanistan_persian_calendar_holidays": [
    { "month": 1, "day": 1, "year": -1, "title": "آغاز عید نوروز" },
    { "month": 1, "day": 2, "year": -1, "title": "روز دهقان" },
    { "month": 2, "day": 8, "year": -1, "title": "سالروز پیروزی مجاهدین در افغانستان" },
    { "month": 5, "day": 28, "year": -1, "title": "روز استقلال کشور" },
    { "month": 6, "day": 18, "year": -1, "title": "روز شهدا" },
    { "month": 11, "day": 26, "year": -1, "title": "شکست و خروج ارتش اتحاد جماهیر شوروی سوسیالیستی سابق از افغانستان" }
  ],
  "afghanistan_hirji_calendar_holidays": [
    { "month": 3, "day": 12, "title": "ولادت حضرت رسول اکرم (ص)" },
    { "month": 10, "day": 1, "title": "عید سعید فطر" },
    { "month": 10, "day": 2, "title": "عید سعید فطر، روز دوم" },
    { "month": 10, "day": 3, "title": "عید سعید فطر، روز سوم" },
    { "month": 12, "day": 9, "title": "روز عرفه (روز نیایش)" },
    { "month": 12, "day": 10, "title": "عید الاضحی (قربان)" },
    { "month": 12, "day": 11, "title": "عید الاضحی (قربان)، روز دوم" },
    { "month": 12, "day": 12, "title": "عید الاضحی (قربان)، روز سوم" }
  ],
  "events": [
    { "holiday": true, "year": -1, "month": 1, "day": 1, "type": "Iran",
      "title": "آغاز عید نوروز" },

    { "holiday": true, "year": -1, "month": 1, "day": 2, "type": "Iran",
      "title": "عید نوروز" },

    { "holiday": false, "year": -1, "month": 1, "day": 2, "type": "Iran",
      "title": "هجوم به مدرسهٔ فیضیهٔ قم (۱۳۴۲ ه‍.ش)" },

    { "holiday": false, "year": -1, "month": 1, "day": 2, "type": "Iran",
      "title": "آغاز عملیات فتح‌المبین (۱۳۶۱ ه‍.ش)" },

    { "holiday": true, "year": -1, "month": 1, "day": 3, "type": "Iran",
      "title": "عید نوروز" },

    { "holiday": true, "year": -1, "month": 1, "day": 4, "type": "Iran",
      "title": "عید نوروز" },

    { "holiday": false, "year": -1, "month": 1, "day": 7, "type": "Iran",
      "title": "روز هنرهای نمایشی" },

    { "holiday": true, "year": -1, "month": 1, "day": 12, "type": "Iran",
      "title": "روز جمهوری اسلامی ایران" },

    { "holiday": true, "year": -1, "month": 1, "day": 13, "type": "Iran",
      "title": "روز طبیعت" },

    { "holiday": false, "year": -1, "month": 1, "day": 18, "type": "Iran",
      "title": "روز سلامتی" },

    { "holiday": false, "year": -1, "month": 1, "day": 20, "type": "Iran",
      "title": "روز ملی فناوری هسته‌ای" },

    { "holiday": false, "year": -1, "month": 1, "day": 20, "type": "Iran",
      "title": "روز هنر انقلاب اسلامی" },

    { "holiday": false, "year": -1, "month": 1, "day": 20, "type": "Iran",
      "title": "شهادت سید مرتضی آوینی (۱۳۷۲ ه‍.ش)" },

    { "holiday": false, "year": -1, "month": 1, "day": 21, "type": "Iran",
      "title": "شهادت امیر سپهبد علی صیاد شیرازی (۱۳۷۸ ه‍.ش)" },

    { "holiday": false, "year": -1, "month": 1, "day": 21, "type": "Iran",
      "title": "سالروز افتتاح حساب شمارهٔ ۱۰۰ و تأسیس بنیاد مسکن انقلاب اسلامی (۱۳۵۸ ه‍.ش)" },

    { "holiday": false, "year": -1, "month": 1, "day": 25, "type": "Iran",
      "title": "روز بزرگداشت عطار نیشابوری" },

    { "holiday": false, "year": -1, "month": 1, "day": 29, "type": "Iran",
      "title": "روز ارتش جمهوری اسلامی و نیروی زمینی" },

    { "holiday": false, "year": -1, "month": 2, "day": 1, "type": "Iran",
      "title": "روز بزرگداشت سعدی" },

    { "holiday": false, "year": -1, "month": 2, "day": 2, "type": "Iran",
      "title": "تأسیس سپاه پاسداران انقلاب اسلامی (۱۳۵۸ ه‍.ش)" },

    { "holiday": false, "year": -1, "month": 2, "day": 2, "type": "Iran",
      "title": "اعلام انقلاب فرهنگی (۱۳۵۹ ه‍.ش)" },

    { "holiday": false, "year": -1, "month": 2, "day": 3, "type": "Iran",
      "title": "روز بزرگداشت شیخ بهایی" },

    { "holiday": false, "year": -1, "month": 2, "day": 5, "type": "Iran",
      "title": "شکست حملهٔ نظامی آمریکا به ایران در طبس (۱۳۵۹ ه‍.ش)" },

    { "holiday": false, "year": -1, "month": 2, "day": 9, "type": "Iran",
      "title": "روز شوراها" },

    { "holiday": false, "year": -1, "month": 2, "day": 10, "type": "Iran",
      "title": "روز ملی خلیج فارس" },

    { "holiday": false, "year": -1, "month": 2, "day": 12, "type": "Iran",
      "title": "شهادت استاد مرتضی مطهری (۱۳۵۸ ه‍.ش)" },

    { "holiday": false, "year": -1, "month": 2, "day": 12, "type": "Iran",
      "title": "روز معلم" },

    { "holiday": false, "year": -1, "month": 2, "day": 12, "type": "Iran",
      "title": "روز جهانی مستضعفان" },

    { "holiday": false, "year": -1, "month": 2, "day": 15, "type": "Iran",
      "title": "روز بزرگداشت شیخ صدوق" },

    { "holiday": false, "year": -1, "month": 2, "day": 18, "type": "Iran",
      "title": "روز بیماری‌های خاص و صعب العلاج" },

    { "holiday": false, "year": -1, "month": 2, "day": 19, "type": "Iran",
      "title": "روز بزرگداشت شیخ کلینی" },

    { "holiday": false, "year": -1, "month": 2, "day": 24, "type": "Iran",
      "title": "لغو امتیاز تنباکو به فتوای آیت‌الله میرزا حسن شیرازی (۱۲۷۰ ه‍.ش)" },

    { "holiday": false, "year": -1, "month": 2, "day": 25, "type": "Iran",
      "title": "روز پاسداشت زبان فارسی و بزرگداشت حکیم ابوالقاسم فردوسی" },

    { "holiday": false, "year": -1, "month": 2, "day": 28, "type": "Iran",
      "title": "روز بزرگداشت حکیم عمر خیام" },

    { "holiday": false, "year": -1, "month": 2, "day": 30, "type": "Iran",
      "title": "روز ملی جمعیت" },

    { "holiday": false, "year": -1, "month": 2, "day": 31, "type": "Iran",
      "title": "روز اهدای عضو، اهدای زندگی" },

    { "holiday": false, "year": -1, "month": 3, "day": 1, "type": "Iran",
      "title": "روز بهره‌وری و بهینه‌سازی مصرف" },

    { "holiday": false, "year": -1, "month": 3, "day": 1, "type": "Iran",
      "title": "روز بزرگداشت ملاصدرا (صدرالمتألهین)" },

    { "holiday": false, "year": -1, "month": 3, "day": 3, "type": "Iran",
      "title": "فتح خرمشهر در عملیات بیت‌المقدس (۱۳۶۱ ه‍.ش)" },

    { "holiday": false, "year": -1, "month": 3, "day": 4, "type": "Iran",
      "title": " روز مقاومت، ایثار و پیروزی" },

    { "holiday": false, "year": -1, "month": 3, "day": 4, "type": "Iran",
      "title": "روز دزفول" },

    { "holiday": false, "year": -1, "month": 3, "day": 4, "type": "Iran",
      "title": "روز مقاومت و پایداری" },

    { "holiday": true, "year": -1, "month": 3, "day": 14, "type": "Iran",
      "title": "رحلت امام خمینی رهبر انقلاب اسلامی (۱۳۶۸ ه‍.ش)" },

    { "holiday": false, "year": -1, "month": 3, "day": 14, "type": "Iran",
      "title": "انتخاب آیت‌الله خامنه‌ای به رهبری (۱۳۶۸ ه‍.ش)" },

    { "holiday": true, "year": -1, "month": 3, "day": 15, "type": "Iran",
      "title": "قیام خونین ۱۵ خرداد (۱۳۴۲ ه‍.ش)" },

    { "holiday": false, "year": -1, "month": 3, "day": 26, "type": "Iran",
      "title": "شهادت سربازان دلیر اسلام: بخارایی، امانی، صفار هندی و نیک‌نژاد (۱۳۴۴ ه‍.ش)" },

    { "holiday": false, "year": -1, "month": 3, "day": 27, "type": "Iran",
      "title": "روز جهاد کشاورزی (تشکیل جهاد سازندگی، ۱۳۵۸ ه‍.ش)" },

    { "holiday": false, "year": -1, "month": 3, "day": 29, "type": "Iran",
      "title": "درگذشت دکتر علی شریعتی (۱۳۵۶ ه‍.ش)" },

    { "holiday": false, "year": -1, "month": 3, "day": 31, "type": "Iran",
      "title": "شهادت دکتر مصطفی چمران (۱۳۶۰ ه‍.ش)" },

    { "holiday": false, "year": -1, "month": 3, "day": 31, "type": "Iran",
      "title": "روز بسیج استادان" },

    { "holiday": false, "year": -1, "month": 4, "day": 1, "type": "Iran",
      "title": "روز تبلیغ و اطلاع‌رسانی دینی (تأسیس سازمان تبلیغات اسلامی ۱۳۶۰ ه‍.ش)" },

    { "holiday": false, "year": -1, "month": 4, "day": 1, "type": "Iran",
      "title": "روز اصناف" },

    { "holiday": false, "year": -1, "month": 4, "day": 7, "type": "Iran",
      "title": "شهادت مظلومانهٔ آیت‌الله دکتر بهشتی و ۷۲ تن از یاران (۱۳۶۰ ه‍.ش)" },

    { "holiday": false, "year": -1, "month": 4, "day": 7, "type": "Iran",
      "title": "روز قوهٔ قضاییه" },

    { "holiday": false, "year": -1, "month": 4, "day": 8, "type": "Iran",
      "title": "روز مبارزه با سلاح‌های شیمیایی و میکروبی" },

    { "holiday": false, "year": -1, "month": 4, "day": 10, "type": "Iran",
      "title": "روز صنعت و معدن" },

    { "holiday": false, "year": -1, "month": 4, "day": 10, "type": "Iran",
      "title": "روز فرهنگ پهلوانی و ورزش زورخانه‌ای" },

    { "holiday": false, "year": -1, "month": 4, "day": 11, "type": "Iran",
      "title": "شهادت آیت‌الله صدوقی (۱۳۶۱ ه‍.ش)" },

    { "holiday": false, "year": -1, "month": 4, "day": 12, "type": "Iran",
      "title": "حملهٔ ناوگان آمریکای به هواپیمای مسافربری ایران (۱۳۶۷ ه‍.ش)" },

    { "holiday": false, "year": -1, "month": 4, "day": 12, "type": "Iran",
      "title": "روز افشای حقوق بشر آمریکایی" },

    { "holiday": false, "year": -1, "month": 4, "day": 14, "type": "Iran",
      "title": "روز قلم" },

    { "holiday": false, "year": -1, "month": 4, "day": 18, "type": "Iran",
      "title": "روز ادبیات کودکان و نوجوانان" },

    { "holiday": false, "year": -1, "month": 4, "day": 21, "type": "Iran",
      "title": "روز عفاف و حجاب" },

    { "holiday": false, "year": -1, "month": 4, "day": 23, "type": "Iran",
      "title": "روز گفت‌وگو و تعامل سازنده با جهان" },

    { "holiday": false, "year": -1, "month": 4, "day": 25, "type": "Iran",
      "title": "روز بهزیستی و تامین اجتماعی" },

    { "holiday": false, "year": -1, "month": 4, "day": 26, "type": "Iran",
      "title": "سالروز تأسیس نهاد شورای نگهبان" },

    { "holiday": false, "year": -1, "month": 4, "day": 28, "type": "Iran",
      "title": "روز تجلیل از امامزادگان و بقاع متبرکه" },

    { "holiday": false, "year": -1, "month": 4, "day": 29, "type": "Iran",
      "title": "روز بزرگداشت حضرت احمد بن موسی شاهچراغ علیه‌السلام" },

    { "holiday": false, "year": -1, "month": 5, "day": 5, "type": "Iran",
      "title": "سالروز عملیات مرصاد (۱۳۶۷ ه‍.ش)" },

    { "holiday": false, "year": -1, "month": 5, "day": 9, "type": "Iran",
      "title": "روز اهدای خون" },

    { "holiday": false, "year": -1, "month": 5, "day": 14, "type": "Iran",
      "title": "صدور فرمان مشروطیت (۱۲۸۵ ه‍.ش)" },

    { "holiday": false, "year": -1, "month": 5, "day": 14, "type": "Iran",
      "title": "روز حقوق بشر اسلامی و کرامت انسانی" },

    { "holiday": false, "year": -1, "month": 5, "day": 16, "type": "Iran",
      "title": "تشکیل جهاد دانشگاهی (۱۳۵۹ ه‍.ش)" },

    { "holiday": false, "year": -1, "month": 5, "day": 17, "type": "Iran",
      "title": "روز خبرنگار" },

    { "holiday": false, "year": -1, "month": 5, "day": 21, "type": "Iran",
      "title": "روز حمایت از صنایع کوچک" },

    { "holiday": false, "year": -1, "month": 5, "day": 22, "type": "Iran",
      "title": "روز تشکل‌ها و مشارکتهای اجتماعی" },

    { "holiday": false, "year": -1, "month": 5, "day": 23, "type": "Iran",
      "title": "روز مقاومت اسلامی" },

    { "holiday": false, "year": -1, "month": 5, "day": 26, "type": "Iran",
      "title": "آغاز بازگشت آزادگان به میهن اسلامی (۱۳۶۹ ه‍.ش)" },

    { "holiday": false, "year": -1, "month": 5, "day": 28, "type": "Iran",
      "title": "کودتای آمریکا برای بازگرداندن شاه (۱۳۳۲ ه‍.ش)" },

    { "holiday": false, "year": -1, "month": 5, "day": 30, "type": "Iran",
      "title": "روز بزرگداشت علامه مجلسی" },

    { "holiday": false, "year": -1, "month": 6, "day": 1, "type": "Iran",
      "title": "روز بزرگداشت ابوعلی سینا" },

    { "holiday": false, "year": -1, "month": 6, "day": 1, "type": "Iran",
      "title": "روز پزشک" },

    { "holiday": false, "year": -1, "month": 6, "day": 2, "type": "Iran",
      "title": "آغاز هفتهٔ دولت" },

    { "holiday": false, "year": -1, "month": 6, "day": 2, "type": "Iran",
      "title": "شهادت سید علی اندرزگو (۱۳۵۷ ه‍.ش)" },

    { "holiday": false, "year": -1, "month": 6, "day": 4, "type": "Iran",
      "title": "روز کارمند" },

    { "holiday": false, "year": -1, "month": 6, "day": 5, "type": "Iran",
      "title": "روز بزرگداشت محمد بن زکریای رازی" },

    { "holiday": false, "year": -1, "month": 6, "day": 5, "type": "Iran",
      "title": "روز داروسازی" },

    { "holiday": false, "year": -1, "month": 6, "day": 5, "type": "Iran",
      "title": "روز کشتی" },

    { "holiday": false, "year": -1, "month": 6, "day": 8, "type": "Iran",
      "title": "روز مبارزه با تروریسم (انفجار دفتر نخست وزیری و شهادت شهیدان رجایی و باهنر - ۱۳۶۰ ه‍.ش)" },

    { "holiday": false, "year": -1, "month": 6, "day": 12, "type": "Iran",
      "title": "روز مبارزه با استعمار انگلیس (سالروز شهادت رئیسعلی دلواری)" },

    { "holiday": false, "year": -1, "month": 6, "day": 13, "type": "Iran",
      "title": "روز تعاون" },

    { "holiday": false, "year": -1, "month": 6, "day": 13, "type": "Iran",
      "title": "روز بزرگداشت ابوریحان بیرونی" },

    { "holiday": false, "year": -1, "month": 6, "day": 14, "type": "Iran",
      "title": "شهادت آیت‌الله قدوسی و سرتیپ وحید دستجردی (۱۳۶۰ ه‍.ش)" },

    { "holiday": false, "year": -1, "month": 6, "day": 17, "type": "Iran",
      "title": "قیام ۱۷ شهریور و کشتار جمعی از مردم به دست مأموران پهلوی (۱۳۵۷ ه‍.ش)" },

    { "holiday": false, "year": -1, "month": 6, "day": 19, "type": "Iran",
      "title": "وفات آیت‌الله سید محمود طالقانی اولین امام جمعهٔ تهران (۱۳۵۸ ه‍.ش)" },

    { "holiday": false, "year": -1, "month": 6, "day": 20, "type": "Iran",
      "title": "شهادت آیت‌الله مدنی (۱۳۶۰ ه‍.ش)" },

    { "holiday": false, "year": -1, "month": 6, "day": 21, "type": "Iran",
      "title": "روز سینما" },

    { "holiday": false, "year": -1, "month": 6, "day": 27, "type": "Iran",
      "title": "روز شعر و ادب فارسی" },

    { "holiday": false, "year": -1, "month": 6, "day": 27, "type": "Iran",
      "title": "روز بزرگداشت استاد سید محمد حسین شهریار" },

    { "holiday": false, "year": -1, "month": 6, "day": 30, "type": "Iran",
      "title": "روز تجلیل از اسرا و مفقودان" },

    { "holiday": false, "year": -1, "month": 6, "day": 31, "type": "Iran",
      "title": "آغاز جنگ تحمیلی (۱۳۵۹ ه‍.ش)" },

    { "holiday": false, "year": -1, "month": 6, "day": 31, "type": "Iran",
      "title": "آغاز هفتهٔ دفاع مقدس" },

    { "holiday": false, "year": -1, "month": 7, "day": 5, "type": "Iran",
      "title": "شکست حصر آبادان در عملیات ثامن‌الأئمه (ع) (۱۳۶۰ ه‍.ش)" },

    { "holiday": false, "year": -1, "month": 7, "day": 7, "type": "Iran",
      "title": "روز بزرگداشت فرماندهان شهید دفاع مقدس" },

    { "holiday": false, "year": -1, "month": 7, "day": 7, "type": "Iran",
      "title": "شهادت سرداران اسلام: فلاحی، فکوری، نامحو، کلاهدوز و جهان‌آرا (۱۳۶۰ ه‍.ش)" },

    { "holiday": false, "year": -1, "month": 7, "day": 7, "type": "Iran",
      "title": "روز آتش‌نشانی و ایمنی" },

    { "holiday": false, "year": -1, "month": 7, "day": 7, "type": "Iran",
      "title": "روز بزرگداشت شمس" },

    { "holiday": false, "year": -1, "month": 7, "day": 8, "type": "Iran",
      "title": "روز بزرگداشت مولوی" },

    { "holiday": false, "year": -1, "month": 7, "day": 9, "type": "Iran",
      "title": "روز همبستگی و همدردی با کودکان و نوجوانان فلسطینی" },

    { "holiday": false, "year": -1, "month": 7, "day": 13, "type": "Iran",
      "title": "هجرت امام خمینی از عراق به پاریس (۱۳۵۷ ه‍.ش)" },

    { "holiday": false, "year": -1, "month": 7, "day": 13, "type": "Iran",
      "title": "روز نیروی انتظامی" },

    { "holiday": false, "year": -1, "month": 7, "day": 14, "type": "Iran",
      "title": "روز دامپزشکی" },

    { "holiday": false, "year": -1, "month": 7, "day": 15, "type": "Iran",
      "title": "روز روستا و عشایر" },

    { "holiday": false, "year": -1, "month": 7, "day": 20, "type": "Iran",
      "title": "روز بزرگداشت حافظ" },

    { "holiday": false, "year": -1, "month": 7, "day": 23, "type": "Iran",
      "title": "شهادت آیت‌الله اشرفی اصفهانی (۱۳۶۱ ه‍.ش)" },

    { "holiday": false, "year": -1, "month": 7, "day": 24, "type": "Iran",
      "title": "روز ملی پارالمپیک" },

    { "holiday": false, "year": -1, "month": 7, "day": 25, "type": "Iran",
      "title": "روز بزرگداشت سلمان فارسی" },

    { "holiday": false, "year": -1, "month": 7, "day": 26, "type": "Iran",
      "title": "روز تربیت بدنی و ورزش" },

    { "holiday": false, "year": -1, "month": 8, "day": 4, "type": "Iran",
      "title": "اعتراض و افشاگری امام خمینی علیه پذیرش کاپیتولاسیون (۱۳۴۳ ه‍.ش)" },

    { "holiday": false, "year": -1, "month": 8, "day": 8, "type": "Iran",
      "title": "شهادت محمد حسین فهمیده (بسیجی ۱۳ ساله)" },

    { "holiday": false, "year": -1, "month": 8, "day": 8, "type": "Iran",
      "title": "روز نوجوان و بسیج دانش‌آموزی" },

    { "holiday": false, "year": -1, "month": 8, "day": 10, "type": "Iran",
      "title": "شهادت آیت‌الله قاضی طباطبایی (۱۳۵۸ ه‍.ش)" },

    { "holiday": false, "year": -1, "month": 8, "day": 13, "type": "Iran",
      "title": "تسخیر لانهٔ جاسوسی آمریکا (۱۳۵۸ ه‍.ش)" },

    { "holiday": false, "year": -1, "month": 8, "day": 13, "type": "Iran",
      "title": "روز ملی مبارزه با استکبار جهانی" },

    { "holiday": false, "year": -1, "month": 8, "day": 13, "type": "Iran",
      "title": "روز دانش‌آموز" },

    { "holiday": false, "year": -1, "month": 8, "day": 14, "type": "Iran",
      "title": "روز فرهنگ عمومی" },

    { "holiday": false, "year": -1, "month": 8, "day": 15, "type": "Iran",
      "title": "روز وقف" },

    { "holiday": false, "year": -1, "month": 8, "day": 24, "type": "Iran",
      "title": "روز کتاب، کتابخوانی و کتابدار" },

    { "holiday": false, "year": -1, "month": 8, "day": 24, "type": "Iran",
      "title": "روز بزرگداشت آیت‌الله علامه سید محمد حسین طباطبایی (۱۳۶۰ ه‍.ش)" },

    { "holiday": false, "year": -1, "month": 9, "day": 5, "type": "Iran",
      "title": "تشکیل بسیج مستضعفان (۱۳۵۸ ه‍.ش)" },

    { "holiday": false, "year": -1, "month": 9, "day": 7, "type": "Iran",
      "title": "روز نیروی دریایی" },

    { "holiday": false, "year": -1, "month": 9, "day": 9, "type": "Iran",
      "title": "روز بزرگداشت شیخ مفید" },

    { "holiday": false, "year": -1, "month": 9, "day": 10, "type": "Iran",
      "title": "شهادت آیت‌الله سید حسن مدرس (۱۳۱۶ ه‍.ش)" },

    { "holiday": false, "year": -1, "month": 9, "day": 10, "type": "Iran",
      "title": "روز مجلس" },

    { "holiday": false, "year": -1, "month": 9, "day": 12, "type": "Iran",
      "title": "روز قانون اساسی جمهوری اسلامی ایران (تصویب قانون اساسی جمهوری اسلامی ایران - ۱۳۵۸ ه‍.ش)" },

    { "holiday": false, "year": -1, "month": 9, "day": 16, "type": "Iran",
      "title": "روز دانشجو" },

    { "holiday": false, "year": -1, "month": 9, "day": 19, "type": "Iran",
      "title": "تشکیل شورای عالی انقلاب فرهنگی (۱۳۶۳ ه‍.ش)" },

    { "holiday": false, "year": -1, "month": 9, "day": 20, "type": "Iran",
      "title": "شهادت آیت‌الله دستغیب (۱۳۶۰ ه‍.ش)" },

    { "holiday": false, "year": -1, "month": 9, "day": 25, "type": "Iran",
      "title": "روز پژوهش" },

    { "holiday": false, "year": -1, "month": 9, "day": 27, "type": "Iran",
      "title": "شهادت آیت‌الله دکتر محمد مفتح (۱۳۵۸ ه‍.ش)" },

    { "holiday": false, "year": -1, "month": 9, "day": 27, "type": "Iran",
      "title": "روز وحدت حوزه و دانشگاه" },

    { "holiday": false, "year": -1, "month": 9, "day": 30, "type": "Iran",
      "title": "شب یلدا (چله)" },

    { "holiday": false, "year": -1, "month": 10, "day": 5, "type": "Iran",
      "title": "روز ایمنی در برابر زلزله و کاهش اثرات بلایای طبیعی" },

    { "holiday": false, "year": -1, "month": 10, "day": 7, "type": "Iran",
      "title": "تشکیل نهضت سوادآموزی (۱۳۵۸ ه‍.ش)" },

    { "holiday": false, "year": -1, "month": 10, "day": 19, "type": "Iran",
      "title": "قیام خونین مردم قم (۱۳۵۶ ه‍.ش)" },

    { "holiday": false, "year": -1, "month": 10, "day": 20, "type": "Iran",
      "title": "شهادت میرزاتقی‌خان امیرکبیر (۱۲۳۰ ه‍.ش)" },

    { "holiday": false, "year": -1, "month": 10, "day": 22, "type": "Iran",
      "title": "تشکیل شورای انقلاب (۱۳۵۷ ه‍.ش)" },

    { "holiday": false, "year": -1, "month": 10, "day": 26, "type": "Iran",
      "title": "فرار شاه (۱۳۵۷ ه‍.ش)" },

    { "holiday": false, "year": -1, "month": 10, "day": 27, "type": "Iran",
      "title": "شهادت نواب صفوی، طهماسبی، برادران واحدی و ذوالقدر از فداییان اسلام (۱۳۳۴ ه‍.ش)" },

    { "holiday": false, "year": -1, "month": 10, "day": 29, "type": "Iran",
      "title": "روز غزه" },

    { "holiday": false, "year": -1, "month": 11, "day": 6, "type": "Iran",
      "title": "سالروز حماسهٔ مردم آمل" },

    { "holiday": false, "year": -1, "month": 11, "day": 12, "type": "Iran",
      "title": "بازگشت امام خمینی به ایران (۱۳۵۷ ه‍.ش) و آغاز دههٔ فجر انقلاب اسلامی" },

    { "holiday": false, "year": -1, "month": 11, "day": 14, "type": "Iran",
      "title": "روز فناوری فضایی" },

    { "holiday": false, "year": -1, "month": 11, "day": 19, "type": "Iran",
      "title": "روز نیروی هوایی" },

    { "holiday": true, "year": -1, "month": 11, "day": 22, "type": "Iran",
      "title": "پیروزی انقلاب اسلامی ایران و سقوط نظام شاهنشاهی (۱۳۵۷ ه‍.ش)" },

    { "holiday": false, "year": -1, "month": 11, "day": 29, "type": "Iran",
      "title": "قیام مردم تبریز به مناسبت چهلمین روز شهادت شهدای قم (۱۳۵۶ ه‍.ش)" },

    { "holiday": false, "year": -1, "month": 11, "day": 29, "type": "Iran",
      "title": "روز اقتصاد مقاومتی و کارآفرینی" },

    { "holiday": false, "year": -1, "month": 12, "day": 5, "type": "Iran",
      "title": "روز بزرگداشت خواجه نصیرالدین طوسی" },

    { "holiday": false, "year": -1, "month": 12, "day": 5, "type": "Iran",
      "title": "روز مهندسی" },

    { "holiday": false, "year": -1, "month": 12, "day": 14, "type": "Iran",
      "title": "روز احسان و نیکوکاری" },

    { "holiday": false, "year": -1, "month": 12, "day": 15, "type": "Iran",
      "title": "روز درختکاری" },

    { "holiday": false, "year": -1, "month": 12, "day": 18, "type": "Iran",
      "title": "روز بزرگداشت سید جمال‌الدین اسدآبادی" },

    { "holiday": false, "year": -1, "month": 12, "day": 18, "type": "Iran",
      "title": "سالروز تأسیس کانون‌های فرهنگی و هنری مساجد کشور" },

    { "holiday": false, "year": -1, "month": 12, "day": 20, "type": "Iran",
      "title": "روز راهیان نور" },

    { "holiday": false, "year": -1, "month": 12, "day": 21, "type": "Iran",
      "title": "روز بزرگداشت نظامی گنجوی" },

    { "holiday": false, "year": -1, "month": 12, "day": 22, "type": "Iran",
      "title": "روز بزرگداشت شهدا (تأسیس بنیاد شهید انقلاب اسلامی - ۱۳۵۸ ه‍.ش)" },

    { "holiday": false, "year": -1, "month": 12, "day": 25, "type": "Iran",
      "title": "روز بزرگداشت پروین اعتصامی" },

    { "holiday": true, "year": -1, "month": 12, "day": 29, "type": "Iran",
      "title": "روز ملی شدن صنعت نفت ایران (۱۳۲۹ ه‍.ش)" },

    { "holiday": false, "year": -1, "month": 1, "day": 10, "type": "Iran",
      "title": "همه‌پرسی تغییر نظام شاهنشاهی به جمهوری اسلامی ایران (۱۳۵۸ ه‍.ش)" },

    { "holiday": false, "year": -1, "month": 1, "day": 15, "type": "Iran",
      "title": "روز ذخایر ژنتیکی و زیستی" },

    { "holiday": false, "year": -1, "month": 1, "day": 19, "type": "Iran",
      "title": "شهادت آیت‌الله سید محمد باقر صدر و خواهر ایشان بنت‌الهدی (۱۳۵۹ ه‍.ش)" },

    { "holiday": false, "year": -1, "month": 1, "day": 20, "type": "Iran",
      "title": "قطع مناسبات سیاسی ایران و آمریکا (۱۳۵۹ ه‍.ش)" },

    { "holiday": false, "year": -1, "month": 2, "day": 2, "type": "Iran",
      "title": "روز زمین پاک" },

    { "holiday": false, "year": -1, "month": 2, "day": 7, "type": "Iran",
      "title": "روز ایمنی حمل و نقل" },

    { "holiday": false, "year": -1, "month": 2, "day": 10, "type": "Iran",
      "title": "آغاز عملیات بیت المقدس (۱۳۶۱ ه‍.ش)" },

    { "holiday": false, "year": -1, "month": 2, "day": 19, "type": "Iran",
      "title": "روز اسناد ملی و میراث مکتوب" },

    { "holiday": false, "year": -1, "month": 2, "day": 27, "type": "Iran",
      "title": "روز ارتباطات و روابط عمومی" },

    { "holiday": false, "year": -1, "month": 3, "day": 5, "type": "Iran",
      "title": "روز نسیم مهر (روز حمایت از خانوادهٔ زندانیان)" },

    { "holiday": false, "year": -1, "month": 3, "day": 7, "type": "Iran",
      "title": "افتتاح اولین دورهٔ مجلس شورای اسلامی (۱۳۵۹ ه‍.ش)" },

    { "holiday": false, "year": -1, "month": 3, "day": 15, "type": "Iran",
      "title": "زندانی شدن امام خمینی (۱۳۴۲ ه‍.ش)" },

    { "holiday": false, "year": -1, "month": 3, "day": 20, "type": "Iran",
      "title": "شهادت آیت‌الله سعیدی (۱۳۴۹ ه‍.ش)" },

    { "holiday": false, "year": -1, "month": 3, "day": 25, "type": "Iran",
      "title": "روز گل و گیاه" },

    { "holiday": false, "year": -1, "month": 3, "day": 30, "type": "Iran",
      "title": "شهادت زائران حرم رضوی (ع) (عاشورای ۱۳۷۳ ه‍.ش)" },

    { "holiday": false, "year": -1, "month": 4, "day": 10, "type": "Iran",
      "title": "روز آزادسازی شهر مهران" },

    { "holiday": false, "year": -1, "month": 4, "day": 12, "type": "Iran",
      "title": "روز بزرگداشت علامه امینی (۱۳۴۹ ه‍.ش)" },

    { "holiday": false, "year": -1, "month": 4, "day": 16, "type": "Iran",
      "title": "روز مالیات" },

    { "holiday": false, "year": -1, "month": 4, "day": 21, "type": "Iran",
      "title": "کشف توطئهٔ کودتای آمریکایی در پایگاه هوایی شهید نوژه (۱۳۵۹ ه‍.ش)" },

    { "holiday": false, "year": -1, "month": 4, "day": 21, "type": "Iran",
      "title": "حمله به مسجد گوهرشاد و کشتار مردم (۱۳۱۴ ه‍.ش)" },

    { "holiday": false, "year": -1, "month": 4, "day": 23, "type": "Iran",
      "title": "گشایش نخستین مجلس خبرگان رهبری (۱۳۶۲ ه‍.ش)" },

    { "holiday": false, "year": -1, "month": 4, "day": 27, "type": "Iran",
      "title": "اعلام پذیرش قطعنامهٔ ۵۹۸ شورای امنیت از سوی ایران (۱۳۶۷ ه‍.ش)" },

    { "holiday": false, "year": -1, "month": 5, "day": 6, "type": "Iran",
      "title": "روز کارآفرینی و آموزش‌های فنی و حرفه‌ای" },

    { "holiday": false, "year": -1, "month": 5, "day": 8, "type": "Iran",
      "title": "روز بزرگداشت شیخ شهاب‌الدین سهروردی (شیخ اشراق)" },

    { "holiday": false, "year": -1, "month": 5, "day": 11, "type": "Iran",
      "title": "شهادت آیت‌الله شیخ فضل‌الله نوری (۱۲۸۸ ه‍.ش)" },

    { "holiday": false, "year": -1, "month": 5, "day": 28, "type": "Iran",
      "title": "گشایش مجلس خبرگان برای بررسی نهایی قانون اساسی جمهوری اسلامی ایران (۱۳۵۸ ه‍.ش)" },

    { "holiday": false, "year": -1, "month": 5, "day": 31, "type": "Iran",
      "title": "روز صنعت دفاعی" },

    { "holiday": false, "year": -1, "month": 6, "day": 10, "type": "Iran",
      "title": "تصویب قانون عملیات بانکی بدون ربا (۱۳۶۲ ه‍.ش)" },

    { "holiday": false, "year": -1, "month": 6, "day": 10, "type": "Iran",
      "title": "روز بانکداری اسلامی" },

    { "holiday": false, "year": -1, "month": 6, "day": 11, "type": "Iran",
      "title": "روز صنعت چاپ" },

    { "holiday": false, "year": -1, "month": 6, "day": 12, "type": "Iran",
      "title": "روز بهورز" },

    { "holiday": false, "year": -1, "month": 6, "day": 30, "type": "Iran",
      "title": "روز گفت‌وگوی تمدن‌ها" },

    { "holiday": false, "year": -1, "month": 7, "day": 20, "type": "Iran",
      "title": "روز اسکان معلولان و سالمندان" },

    { "holiday": false, "year": -1, "month": 7, "day": 24, "type": "Iran",
      "title": "روز پیوند اولیا و مربیان" },

    { "holiday": false, "year": -1, "month": 7, "day": 24, "type": "Iran",
      "title": "به آتش کشیدن مسجد جامع شهر کرمان (۱۳۵۷ ه‍.ش)" },

    { "holiday": false, "year": -1, "month": 7, "day": 29, "type": "Iran",
      "title": "روز صادرات" },

    { "holiday": false, "year": -1, "month": 8, "day": 1, "type": "Iran",
      "title": "شهادت مظلومانهٔ آیت‌الله حاج سید مصطفی خمینی (۱۳۵۶ ه‍.ش)" },

    { "holiday": false, "year": -1, "month": 8, "day": 1, "type": "Iran",
      "title": "روز آمار و برنامه‌ریزی" },

    { "holiday": false, "year": -1, "month": 8, "day": 13, "type": "Iran",
      "title": "تبعید امام خمینی از ایران به ترکیه (۱۳۴۳ ه‍.ش)" },

    { "holiday": false, "year": -1, "month": 8, "day": 18, "type": "Iran",
      "title": "روز کیفیت" },

    { "holiday": false, "year": -1, "month": 8, "day": 26, "type": "Iran",
      "title": "آزادسازی سوسنگرد" },

    { "holiday": false, "year": -1, "month": 9, "day": 11, "type": "Iran",
      "title": "شهادت میرزا کوچک خان جنگلی (۱۳۰۰ ه‍.ش)" },

    { "holiday": false, "year": -1, "month": 9, "day": 13, "type": "Iran",
      "title": "روز بیمه" },

    { "holiday": false, "year": -1, "month": 9, "day": 18, "type": "Iran",
      "title": "معرفی عراق به عنوان مسئول و آغازگر جنگ از سوی سازمان ملل (۱۳۷۰ ه‍.ش)" },

    { "holiday": false, "year": -1, "month": 9, "day": 25, "type": "Iran",
      "title": "روز تجلیل از شهید تندگویان" },

    { "holiday": false, "year": -1, "month": 9, "day": 26, "type": "Iran",
      "title": "روز حمل و نقل و رانندگان" },

    { "holiday": false, "year": -1, "month": 10, "day": 3, "type": "Iran",
      "title": "روز ثبت احوال" },

    { "holiday": false, "year": -1, "month": 10, "day": 5, "type": "Iran",
      "title": "روز ملی ایمنی در برابر زلزله" },

    { "holiday": false, "year": -1, "month": 10, "day": 7, "type": "Iran",
      "title": "شهادت آیت‌الله حسین غفاری (۱۳۵۳ ه‍.ش)" },

    { "holiday": false, "year": -1, "month": 10, "day": 13, "type": "Iran",
      "title": "ابلاغ پیام تاریخی امام خمینی به گورباچف رهبر شوروی سابق (۱۳۶۷ ه‍.ش)" },

    { "holiday": false, "year": -1, "month": 10, "day": 17, "type": "Iran",
      "title": "اجرای طرح استعماری حذف حجاب (۱۳۱۴ ه‍.ش)" },

    { "holiday": false, "year": -1, "month": 11, "day": 5, "type": "Iran",
      "title": "انتخابات اولین دورهٔ ریاست جمهوری (۱۳۵۸ ه‍.ش)" },

    { "holiday": false, "year": -1, "month": 11, "day": 21, "type": "Iran",
      "title": "شکسته شدن حکومت نظامی به فرمان امام خمینی (۱۳۵۷ ه‍.ش)" },

    { "holiday": false, "year": -1, "month": 11, "day": 25, "type": "Iran",
      "title": "صدور حکم امام خمینی مبنی بر ارتداد سلمان رشدی (۱۳۶۷ ه‍.ش)" },

    { "holiday": false, "year": -1, "month": 12, "day": 3, "type": "Iran",
      "title": "کودتای رضاخان (۱۲۹۹ ه‍.ش)" },

    { "holiday": false, "year": -1, "month": 12, "day": 8, "type": "Iran",
      "title": "روز امور تربیتی و تربیت اسلامی" },

    { "holiday": false, "year": -1, "month": 12, "day": 9, "type": "Iran",
      "title": "روز ملی حمایت از حقوق مصرف‌کنندگان" },

    { "holiday": false, "year": -1, "month": 12, "day": 24, "type": "Iran",
      "title": "برگزاری انتخابات اولین دورهٔ مجلس شورای اسلامی (۱۳۵۸ ه‍.ش)" },

    { "holiday": false, "year": -1, "month": 12, "day": 25, "type": "Iran",
      "title": "بمباران شیمیایی حلبچه توسط ارتش بعث عراق (۱۳۶۶ ه‍.ش)" },

    { "holiday": false, "year": -1, "month": 1, "day": 6, "type": "Ancient Iran",
      "title": "روز امید، روز شادباش‌نویسی" },

    { "holiday": false, "year": -1, "month": 1, "day": 10, "type": "Ancient Iran",
      "title": "جشن آبانگاه" },

    { "holiday": false, "year": -1, "month": 1, "day": 13, "type": "Ancient Iran",
      "title": "جشن سیزده‌بدر" },

    { "holiday": false, "year": -1, "month": 1, "day": 17, "type": "Ancient Iran",
      "title": "سروش‌روز، جشن سروشگان" },

    { "holiday": false, "year": -1, "month": 1, "day": 19, "type": "Ancient Iran",
      "title": "فرورین‌روز، جشن فروردینگان" },

    { "holiday": false, "year": -1, "month": 2, "day": 2, "type": "Ancient Iran",
      "title": "جشن گیاه‌آوری" },

    { "holiday": false, "year": -1, "month": 2, "day": 3, "type": "Ancient Iran",
      "title": "اردیبهشت‌روز، جشن اردیبهشتگان" },

    { "holiday": false, "year": -1, "month": 2, "day": 10, "type": "Ancient Iran",
      "title": "جشن چهلم نوروز" },

    { "holiday": false, "year": -1, "month": 2, "day": 15, "type": "Ancient Iran",
      "title": "گاهنبار میدیوزَرِم، جشن میانهٔ بهار، جشن بهاربُد / روز پیام‌آوری زرتشت" },

    { "holiday": false, "year": -1, "month": 3, "day": 1, "type": "Ancient Iran",
      "title": "ارغاسوان، جشن گرما" },

    { "holiday": false, "year": -1, "month": 3, "day": 6, "type": "Ancient Iran",
      "title": "خردادروز، جشن خردادگان" },

    { "holiday": false, "year": -1, "month": 4, "day": 1, "type": "Ancient Iran",
      "title": "جشن آب‌پاشونک، جشن آغاز تابستان / سال نو در گاهشماری گاهنباری / دیدار طلوع خورشید در تقویم آفتابی چارتاقی نیاسر" },

    { "holiday": false, "year": -1, "month": 4, "day": 6, "type": "Ancient Iran",
      "title": "جشن نیلوفر" },

    { "holiday": false, "year": -1, "month": 4, "day": 13, "type": "Ancient Iran",
      "title": "تیرروز، جشن تیرگان" },

    { "holiday": false, "year": -1, "month": 4, "day": 15, "type": "Ancient Iran",
      "title": "جشن خام‌خواری" },

    { "holiday": false, "year": -1, "month": 5, "day": 7, "type": "Ancient Iran",
      "title": "مردادروز، جشن مردادگان" },

    { "holiday": false, "year": -1, "month": 5, "day": 10, "type": "Ancient Iran",
      "title": "جشن چلهٔ تابستان" },

    { "holiday": false, "year": -1, "month": 5, "day": 15, "type": "Ancient Iran",
      "title": "گاهنبار میدیوشِم، جشن میانهٔ تابستان" },

    { "holiday": false, "year": -1, "month": 5, "day": 18, "type": "Ancient Iran",
      "title": "جشن مَی‌خواره" },

    { "holiday": false, "year": -1, "month": 6, "day": 1, "type": "Ancient Iran",
      "title": "فغدیه، جشن خنکی هوا" },

    { "holiday": false, "year": -1, "month": 6, "day": 3, "type": "Ancient Iran",
      "title": "جشن کشمین" },

    { "holiday": false, "year": -1, "month": 6, "day": 4, "type": "Ancient Iran",
      "title": "شهریورروز، جشن شهریورگان / زادروز داراب (کوروش) / عروج مانی" },

    { "holiday": false, "year": -1, "month": 6, "day": 8, "type": "Ancient Iran",
      "title": "خزان‌جشن" },

    { "holiday": false, "year": -1, "month": 6, "day": 15, "type": "Ancient Iran",
      "title": "بازارجشن" },

    { "holiday": false, "year": -1, "month": 6, "day": 31, "type": "Ancient Iran",
      "title": "گاهنبار پَتیَه‌شَهیم، جشن پایان تابستان" },

    { "holiday": false, "year": -1, "month": 7, "day": 1, "type": "Ancient Iran",
      "title": "جشن میتراکانا / سال نو هخامنشی" },

    { "holiday": false, "year": -1, "month": 7, "day": 12, "type": "Ancient Iran",
      "title": "آیین قالیشویان اردهال، بازماندی از تیرگان" },

    { "holiday": false, "year": -1, "month": 7, "day": 13, "type": "Ancient Iran",
      "title": "تیرروز، جشن تیرروزی" },

    { "holiday": false, "year": -1, "month": 7, "day": 16, "type": "Ancient Iran",
      "title": "مهرروز، جشن مهرگان" },

    { "holiday": false, "year": -1, "month": 7, "day": 21, "type": "Ancient Iran",
      "title": "رام‌روز، جشن رام‌روزی / جشن پیروزی کاوه و فریدون" },

    { "holiday": false, "year": -1, "month": 8, "day": 10, "type": "Ancient Iran",
      "title": "آبان‌روز، جشن آبانگان" },

    { "holiday": false, "year": -1, "month": 8, "day": 15, "type": "Ancient Iran",
      "title": "گاهنبار اَیاثرَم، جشن میانهٔ پاییز" },

    { "holiday": false, "year": -1, "month": 9, "day": 1, "type": "Ancient Iran",
      "title": "آذرجشن" },

    { "holiday": false, "year": -1, "month": 9, "day": 9, "type": "Ancient Iran",
      "title": "آذرروز، جشن آذرگان" },

    { "holiday": false, "year": -1, "month": 9, "day": 30, "type": "Ancient Iran",
      "title": "گاهنبار میدیارِم، جشن میانهٔ سال گاهنباری (از مبدأ آغاز تابستان)" },

    { "holiday": false, "year": -1, "month": 10, "day": 1, "type": "Ancient Iran",
      "title": "روز میلاد خورشید، جشن خرم‌روز / نخستین جشن دیگان / دیدار طلوع خورشید در تقویم آفتابی چارتاقی نیاسر" },

    { "holiday": false, "year": -1, "month": 10, "day": 5, "type": "Ancient Iran",
      "title": "بازارجشن" },

    { "holiday": false, "year": -1, "month": 10, "day": 8, "type": "Ancient Iran",
      "title": "دی‌به‌آذرروز، دومین جشن دیگان" },

    { "holiday": false, "year": -1, "month": 10, "day": 14, "type": "Ancient Iran",
      "title": "سیرسور، جشن گیاه‌خواری" },

    { "holiday": false, "year": -1, "month": 10, "day": 15, "type": "Ancient Iran",
      "title": "جشن پیکرتراشی / دی‌به‌مهرروز، سومین جشن دیگان" },

    { "holiday": false, "year": -1, "month": 10, "day": 16, "type": "Ancient Iran",
      "title": "جشن درامزینان، جشن درفش‌ها" },

    { "holiday": false, "year": -1, "month": 10, "day": 23, "type": "Ancient Iran",
      "title": "دی‌به‌دین‌روز، چهارمین جشن دیگان" },

    { "holiday": false, "year": -1, "month": 11, "day": 1, "type": "Ancient Iran",
      "title": "زادروز فردوسی" },

    { "holiday": false, "year": -1, "month": 11, "day": 2, "type": "Ancient Iran",
      "title": "بهمن‌روز، جشن بهمنگان" },

    { "holiday": false, "year": -1, "month": 11, "day": 4, "type": "Ancient Iran",
      "title": "شهریورروز، آغاز پادشاهی داراب (کوروش)" },

    { "holiday": false, "year": -1, "month": 11, "day": 5, "type": "Ancient Iran",
      "title": "جشن نوسَره" },

    { "holiday": false, "year": -1, "month": 11, "day": 10, "type": "Ancient Iran",
      "title": "آبان‌روز، جشن سَدَه، آتش‌افروزی بر بام‌ها / نمایش‌بازی همگانی" },

    { "holiday": false, "year": -1, "month": 11, "day": 15, "type": "Ancient Iran",
      "title": "جشن میانهٔ زمستان" },

    { "holiday": false, "year": -1, "month": 11, "day": 22, "type": "Ancient Iran",
      "title": "بادروز، جشن بادروزی" },

    { "holiday": false, "year": -1, "month": 12, "day": 1, "type": "Ancient Iran",
      "title": "جشن اسفندی / جشن آبسالان، بهارجشن / نمایش‌بازی همگانی" },

    { "holiday": false, "year": -1, "month": 12, "day": 5, "type": "Ancient Iran",
      "title": "اسفندروز، جشن اسفندگان، گرامیداشت زمین و بانوان / جشن برزگران" },

    { "holiday": false, "year": -1, "month": 12, "day": 10, "type": "Ancient Iran",
      "title": "جشن وخشنکام" },

    { "holiday": false, "year": -1, "month": 12, "day": 19, "type": "Ancient Iran",
      "title": "جشن نوروز رودها" },

    { "holiday": false, "year": -1, "month": 12, "day": 20, "type": "Ancient Iran",
      "title": "جشن گلدان" },

    { "holiday": false, "year": -1, "month": 12, "day": 25, "type": "Ancient Iran",
      "title": "هزارهٔ شاهنامه، هزارمین سالگرد پایان سرایش شاهنامهٔ فرودسی" },

    { "holiday": false, "year": -1, "month": 12, "day": 26, "type": "Ancient Iran",
      "title": "فروردگان" },

    { "holiday": false, "year": -1, "month": 12, "day": 29, "type": "Ancient Iran",
      "title": "گاهنبار هَمَسپَتمَدَم، جشن پایان زمستان (در آخرین روز سال) / زادروز زرتشت / جشن اوشیدر (نجات‌بخش ایرانی) در دریاچهٔ هامون و کوه خواجه / آتش‌افروزی بر بام‌ها در استقبال از نوروز" },

    { "holiday": true, "year": 1394, "month": 1, "day": 4, "type": "Islamic",
      "title": "شهادت حضرت فاطمه زهرا سلام الله علیها (۱۱ ه‍.ق)" },

    { "holiday": true, "year": 1394, "month": 2, "day": 12, "type": "Islamic",
      "title": "ولادت حضرت امام علی علیه‌السلام (۲۳ سال قبل از هجرت)" },

    { "holiday": true, "year": 1394, "month": 2, "day": 26, "type": "Islamic",
      "title": "مبعث حضرت رسول اکرم (ص) (۱۳ سال قبل از هجرت)" },

    { "holiday": true, "year": 1394, "month": 3, "day": 13, "type": "Islamic",
      "title": "ولادت حضرت قائم عجل الله تعالی فرجه (۲۵۵ ه‍.ق)" },

    { "holiday": true, "year": 1394, "month": 4, "day": 17, "type": "Islamic",
      "title": "شهادت حضرت علی علیه‌السلام (۴۰ ه‍.ق)" },

    { "holiday": true, "year": 1394, "month": 4, "day": 27, "type": "Islamic",
      "title": "عید سعید فطر" },

    { "holiday": true, "year": 1394, "month": 4, "day": 28, "type": "Islamic",
      "title": "تعطیل به مناسبت عید سعید فطر" },

    { "holiday": true, "year": 1394, "month": 5, "day": 20, "type": "Islamic",
      "title": "شهادت حضرت امام جعفر صادق علیه‌السلام (۱۴۸ ه‍.ق)" },

    { "holiday": true, "year": 1394, "month": 7, "day": 2, "type": "Islamic",
      "title": "عید سعید قربان" },

    { "holiday": true, "year": 1394, "month": 7, "day": 10, "type": "Islamic",
      "title": "عید سعید غدیر خم (۱۰ ه‍.ق)" },

    { "holiday": true, "year": 1394, "month": 8, "day": 1, "type": "Islamic",
      "title": "تاسوعای حسینی" },

    { "holiday": true, "year": 1394, "month": 8, "day": 2, "type": "Islamic",
      "title": "عاشورای حسینی" },

    { "holiday": true, "year": 1394, "month": 9, "day": 11, "type": "Islamic",
      "title": "اربعین حسینی" },

    { "holiday": true, "year": 1394, "month": 9, "day": 19, "type": "Islamic",
      "title": "رحلت حضرت رسول اکرم (ص) (۱۱ ه‍.ق)" },

    { "holiday": true, "year": 1394, "month": 9, "day": 19, "type": "Islamic",
      "title": "شهادت حضرت امام حسن مجتبی علیه‌السلام (۵۰ ه‍.ق)" },

    { "holiday": true, "year": 1394, "month": 9, "day": 21, "type": "Islamic",
      "title": "شهادت حضرت امام رضا علیه‌السلام (۲۰۳ ه‍.ق)" },

    { "holiday": true, "year": 1394, "month": 10, "day": 8, "type": "Islamic",
      "title": "میلاد حضرت رسول اکرم (ص) (۵۳ سال قبل از هجرت)" },

    { "holiday": false, "year": 1394, "month": 10, "day": 8, "type": "Islamic",
      "title": "میلاد حضرت امام جعفر صادق علیه‌السلام مؤسس مذهب جعفری (۸۳ ه‍.ق)" },

    { "holiday": true, "year": 1394, "month": 12, "day": 23, "type": "Islamic",
      "title": "شهادت حضرت فاطمه زهرا سلام الله علیها (۱۱ ه‍.ق)" },

    { "holiday": true, "year": 1395, "month": 1, "day": 4, "type": "Islamic",
      "title": "سالروز وفات حضرت ام‌البنین سلام الله علیها" },

    { "holiday": true, "year": 1395, "month": 2, "day": 2, "type": "Islamic",
      "title": "ولادت حضرت امام علی علیه‌السلام (۲۳ سال قبل از هجرت)" },

    { "holiday": true, "year": 1395, "month": 2, "day": 16, "type": "Islamic",
      "title": "مبعث حضرت رسول اکرم (ص) (۱۳ سال قبل از هجرت)" },

    { "holiday": true, "year": 1395, "month": 3, "day": 2, "type": "Islamic",
      "title": "ولادت حضرت قائم عجل الله تعالی فرجه (۲۵۵ ه‍.ق)" },

    { "holiday": true, "year": 1395, "month": 4, "day": 7, "type": "Islamic",
      "title": "شهادت حضرت علی علیه‌السلام (۴۰ ه‍.ق)" },

    { "holiday": true, "year": 1395, "month": 4, "day": 16, "type": "Islamic",
      "title": "عید سعید فطر" },

    { "holiday": true, "year": 1395, "month": 4, "day": 17, "type": "Islamic",
      "title": "تعطیل به مناسبت عید سعید فطر" },

    { "holiday": true, "year": 1395, "month": 5, "day": 9, "type": "Islamic",
      "title": "شهادت حضرت امام جعفر صادق علیه‌السلام (۱۴۸ ه‍.ق)" },

    { "holiday": true, "year": 1395, "month": 6, "day": 22, "type": "Islamic",
      "title": "عید سعید قربان" },

    { "holiday": true, "year": 1395, "month": 6, "day": 30, "type": "Islamic",
      "title": "عید سعید غدیر خم (۱۰ ه‍.ق)" },

    { "holiday": true, "year": 1395, "month": 7, "day": 20, "type": "Islamic",
      "title": "تاسوعای حسینی" },

    { "holiday": true, "year": 1395, "month": 7, "day": 21, "type": "Islamic",
      "title": "عاشورای حسینی" },

    { "holiday": true, "year": 1395, "month": 8, "day": 30, "type": "Islamic",
      "title": "اربعین حسینی" },

    { "holiday": true, "year": 1395, "month": 9, "day": 8, "type": "Islamic",
      "title": "رحلت حضرت رسول اکرم (ص) (۱۱ ه‍.ق)" },

    { "holiday": true, "year": 1395, "month": 9, "day": 8, "type": "Islamic",
      "title": "شهادت حضرت امام حسن مجتبی علیه‌السلام (۵۰ ه‍.ق)" },

    { "holiday": true, "year": 1395, "month": 9, "day": 10, "type": "Islamic",
      "title": "شهادت حضرت امام رضا علیه‌السلام (۲۰۳ ه‍.ق)" },

    { "holiday": true, "year": 1395, "month": 9, "day": 27, "type": "Islamic",
      "title": "میلاد حضرت رسول اکرم (ص) (۵۳ سال قبل از هجرت)" },

    { "holiday": false, "year": 1395, "month": 9, "day": 27, "type": "Islamic",
      "title": "میلاد حضرت امام جعفر صادق علیه‌السلام مؤسس مذهب جعفری (۸۳ ه‍.ق)" },

    { "holiday": true, "year": 1395, "month": 12, "day": 12, "type": "Islamic",
      "title": "شهادت حضرت فاطمه زهرا سلام الله علیها (۱۱ ه‍.ق)" },

    { "holiday": true, "year": 1396, "month": 1, "day": 22, "type": "Islamic",
      "title": "ولادت حضرت امام علی علیه‌السلام (۲۳ سال قبل از هجرت)" },

    { "holiday": true, "year": 1396, "month": 2, "day": 5, "type": "Islamic",
      "title": "مبعث حضرت رسول اکرم (ص) (۱۳ سال قبل از هجرت)" },

    { "holiday": true, "year": 1396, "month": 2, "day": 22, "type": "Islamic",
      "title": "ولادت حضرت قائم عجل الله تعالی فرجه (۲۵۵ ه‍.ق)" },

    { "holiday": true, "year": 1396, "month": 3, "day": 26, "type": "Islamic",
      "title": "شهادت حضرت علی علیه‌السلام (۴۰ ه‍.ق)" },

    { "holiday": true, "year": 1396, "month": 4, "day": 5, "type": "Islamic",
      "title": "عید سعید فطر" },

    { "holiday": true, "year": 1396, "month": 4, "day": 6, "type": "Islamic",
      "title": "تعطیل به مناسبت عید سعید فطر" },

    { "holiday": true, "year": 1396, "month": 4, "day": 29, "type": "Islamic",
      "title": "شهادت حضرت امام جعفر صادق علیه‌السلام (۱۴۸ ه‍.ق)" },

    { "holiday": true, "year": 1396, "month": 6, "day": 10, "type": "Islamic",
      "title": "عید سعید قربان" },

    { "holiday": true, "year": 1396, "month": 6, "day": 18, "type": "Islamic",
      "title": "عید سعید غدیر خم (۱۰ ه‍.ق)" },

    { "holiday": true, "year": 1396, "month": 7, "day": 8, "type": "Islamic",
      "title": "تاسوعای حسینی" },

    { "holiday": true, "year": 1396, "month": 7, "day": 9, "type": "Islamic",
      "title": "عاشورای حسینی" },

    { "holiday": true, "year": 1396, "month": 8, "day": 18, "type": "Islamic",
      "title": "اربعین حسینی" },

    { "holiday": true, "year": 1396, "month": 8, "day": 26, "type": "Islamic",
      "title": "رحلت حضرت رسول اکرم (ص) (۱۱ ه‍.ق)" },

    { "holiday": true, "year": 1396, "month": 8, "day": 26, "type": "Islamic",
      "title": "شهادت حضرت امام حسن مجتبی علیه‌السلام (۵۰ ه‍.ق)" },

    { "holiday": true, "year": 1396, "month": 8, "day": 28, "type": "Islamic",
      "title": "شهادت حضرت امام رضا علیه‌السلام (۲۰۳ ه‍.ق)" },

    { "holiday": true, "year": 1396, "month": 9, "day": 6, "type": "Islamic",
      "title": "شهادت حضرت امام حسن عسکری علیه‌السلام (۲۶۰ ه‍.ق) و آغاز امامت حضرت ولیعصر عجل‌الله تعالی فرجه" },

    { "holiday": true, "year": 1396, "month": 9, "day": 15, "type": "Islamic",
      "title": "میلاد حضرت رسول اکرم (ص) (۵۳ سال قبل از هجرت)" },

    { "holiday": false, "year": 1396, "month": 9, "day": 15, "type": "Islamic",
      "title": "میلاد حضرت امام جعفر صادق علیه‌السلام مؤسس مذهب جعفری (۸۳ ه‍.ق)" },

    { "holiday": true, "year": 1396, "month": 12, "day": 1, "type": "Islamic",
      "title": "شهادت حضرت فاطمه زهرا سلام الله علیها (۱۱ ه‍.ق)" },

    { "holiday": false, "year": 1397, "month": 1, "day": 8, "type": "Islamic",
      "title": "ولادت حضرت امام محمد تقی علیه‌السلام «جواد الائمه» (۱۹۵ ه‍.ق)" },

    { "holiday": true, "year": 1397, "month": 1, "day": 11, "type": "Islamic",
      "title": "ولادت حضرت امام علی علیه‌السلام (۲۳ سال قبل از هجرت)" },

    { "holiday": false, "year": 1397, "month": 1, "day": 13, "type": "Islamic",
      "title": "وفات حضرت زینب سلام الله علیها (۶۲ ه‍.ق)" },

    { "holiday": false, "year": 1397, "month": 1, "day": 13, "type": "Islamic",
      "title": "تغییر قبلهٔ مسلمین از بیت المقدس به مکه معظمه (۲ ه‍.ق)" },

    { "holiday": false, "year": 1397, "month": 1, "day": 23, "type": "Islamic",
      "title": "شهادت حضرت امام موسی کاظم علیه السلام (۱۸۳ ه‍.ق)" },

    { "holiday": true, "year": 1397, "month": 1, "day": 25, "type": "Islamic",
      "title": "مبعث حضرت رسول اکرم (ص) (۱۳ سال قبل از هجرت)" },

    { "holiday": false, "year": 1397, "month": 1, "day": 31, "type": "Islamic",
      "title": "ولادت حضرت امام حسین علیه‌السلام (۴ ه‍.ق) و روز پاسدار" },

    { "holiday": false, "year": 1397, "month": 2, "day": 1, "type": "Islamic",
      "title": "ولادت حضرت ابوالفضل العباس علیه السلام (۲۶ ه‍.ق) و روز جانباز" },

    { "holiday": false, "year": 1397, "month": 2, "day": 2, "type": "Islamic",
      "title": "ولادت حضرت امام زین‌العابدین علیه‌السلام (۳۸ ه‍.ق)" },

    { "holiday": false, "year": 1397, "month": 2, "day": 8, "type": "Islamic",
      "title": "ولادت حضرت علی اکبر علیه‌السلام (۳۳ ه‍.ق) و روز جوان" },

    { "holiday": true, "year": 1397, "month": 2, "day": 12, "type": "Islamic",
      "title": "ولادت حضرت قائم عجل الله تعالی فرجه (۲۵۵ ه‍.ق)" },

    { "holiday": false, "year": 1397, "month": 3, "day": 5, "type": "Islamic",
      "title": "وفات حضرت خدیجه سلام الله علیها (۳ سال قبل از هجرت)" },

    { "holiday": false, "year": 1397, "month": 3, "day": 10, "type": "Islamic",
      "title": "ولادت حضرت امام حسن مجتبی علیه‌السلام (۳ ه‍.ق) و روز اکرام" },

    { "holiday": false, "year": 1397, "month": 3, "day": 13, "type": "Islamic",
      "title": "شب قدر" },

    { "holiday": false, "year": 1397, "month": 3, "day": 14, "type": "Islamic",
      "title": "ضربت خوردن حضرت امام علی علیه‌السلام (۴۰ ه‍.ق)" },

    { "holiday": true, "year": 1397, "month": 3, "day": 16, "type": "Islamic",
      "title": "شهادت حضرت علی علیه‌السلام (۴۰ ه‍.ق)" },

    { "holiday": false, "year": 1397, "month": 3, "day": 15, "type": "Islamic",
      "title": "شب قدر" },

    { "holiday": false, "year": 1397, "month": 3, "day": 17, "type": "Islamic",
      "title": "شب قدر" },

    { "holiday": false, "year": 1397, "month": 3, "day": 18, "type": "Islamic",
      "title": "روز جهانی قدس (آخرین جمعه ماه رمضان)" },

    { "holiday": true, "year": 1397, "month": 3, "day": 25, "type": "Islamic",
      "title": "عید سعید فطر" },

    { "holiday": true, "year": 1397, "month": 3, "day": 26, "type": "Islamic",
      "title": "تعطیل به مناسبت عید سعید فطر" },

    { "holiday": true, "year": 1397, "month": 4, "day": 18, "type": "Islamic",
      "title": "شهادت حضرت امام جعفر صادق علیه‌السلام (۱۴۸ ه‍.ق)" },

    { "holiday": false, "year": 1397, "month": 4, "day": 24, "type": "Islamic",
      "title": "ولادت حضرت معصومه سلام الله علیها (۱۳۷ ه‍.ق) و روز دختران" },

    { "holiday": false, "year": 1397, "month": 5, "day": 3, "type": "Islamic",
      "title": "ولادت حضرت امام رضا علیه السلام (۱۴۸ ه‍.ق)" },

    { "holiday": false, "year": 1397, "month": 5, "day": 30, "type": "Islamic",
      "title": "روز عرفه (روز نیایش)" },

    { "holiday": true, "year": 1397, "month": 5, "day": 31, "type": "Islamic",
      "title": "عید سعید قربان" },

    { "holiday": true, "year": 1397, "month": 6, "day": 8, "type": "Islamic",
      "title": "عید سعید غدیر خم (۱۰ ه‍.ق)" },

    { "holiday": true, "year": 1397, "month": 6, "day": 28, "type": "Islamic",
      "title": "تاسوعای حسینی" },

    { "holiday": true, "year": 1397, "month": 6, "day": 29, "type": "Islamic",
      "title": "عاشورای حسینی" },

    { "holiday": false, "year": 1397, "month": 6, "day": 31, "type": "Islamic",
      "title": "شهادت حضرت امام زین‌العابدین علیه السلام (۹۵ ه‍.ق) " },

    { "holiday": true, "year": 1397, "month": 8, "day": 8, "type": "Islamic",
      "title": "اربعین حسینی" },

    { "holiday": true, "year": 1397, "month": 8, "day": 16, "type": "Islamic",
      "title": "رحلت حضرت رسول اکرم (ص) (۱۱ ه‍.ق)" },

    { "holiday": true, "year": 1397, "month": 8, "day": 16, "type": "Islamic",
      "title": "شهادت حضرت امام حسن مجتبی علیه‌السلام (۵۰ ه‍.ق)" },

    { "holiday": true, "year": 1397, "month": 8, "day": 17, "type": "Islamic",
      "title": "شهادت حضرت امام رضا علیه‌السلام (۲۰۳ ه‍.ق)" },

    { "holiday": false, "year": 1397, "month": 8, "day": 18, "type": "Islamic",
      "title": "هجرت حضرت رسول اکرم (ص) از مکه به مدینه" },

    { "holiday": true, "year": 1397, "month": 8, "day": 25, "type": "Islamic",
      "title": "شهادت حضرت امام حسن عسکری علیه‌السلام (۲۶۰ ه‍.ق) و آغاز امامت حضرت ولیعصر عجل‌الله تعالی فرجه" },

    { "holiday": false, "year": 1397, "month": 8, "day": 29, "type": "Islamic",
      "title": "ولادت حضرت رسول اکرم صلی‌الله علیه و آله به روایت اهل سنت (۵۳ سال قبل از هجرت) و آغاز هفته وحدت" },

    { "holiday": true, "year": 1397, "month": 9, "day": 4, "type": "Islamic",
      "title": "ولادت حضرت رسول اکرم (ص) (۵۳ سال قبل از هجرت) و روز اخلاق و مهرورزی" },

    { "holiday": false, "year": 1397, "month": 9, "day": 4, "type": "Islamic",
      "title": "میلاد حضرت امام جعفر صادق علیه‌السلام مؤسس مذهب جعفری (۸۳ ه‍.ق)" },

    { "holiday": false, "year": 1397, "month": 10, "day": 22, "type": "Islamic",
      "title": "ولادت حضرت زینب سلام الله علیها (۵ ه‍.ق) و روز پرستار" },

    { "holiday": false, "year": 1397, "month": 10, "day": 30, "type": "Islamic",
      "title": "شهادت حضرت فاطمة زهرا سلام الله علیها (۱۱ ه‍.ق) به روایتی" },

    { "holiday": true, "year": 1397, "month": 11, "day": 20, "type": "Islamic",
      "title": "شهادت حضرت فاطمة زهرا سلام الله علیها (۱۱ ه‍.ق)" },

    { "holiday": false, "year": 1397, "month": 11, "day": 30, "type": "Islamic",
      "title": "سالروز وفات حضرت ام‌البنین سلام الله علیها" },

    { "holiday": false, "year": 1397, "month": 12, "day": 8, "type": "Islamic",
      "title": "ولادت حضرت فاطمة زهرا سلام الله علیها (هشتم قبل از هجرت) و روز زن - تولد حضرت امام خمینی (۱۳۲۰ ه‍.ق)" },

    { "holiday": false, "year": 1397, "month": 12, "day": 17, "type": "Islamic",
      "title": "ولادت حضرت امام محمد باقر علیه‌السلام (۵۷ ه‍.ق)" },

    { "holiday": true, "year": 1397, "month": 12, "day": 29, "type": "Islamic",
      "title": "ولادت حضرت امام علی علیه‌السلام (۲۳ سال قبل از هجرت)" }
  ],

  "hijri_islamic_events": [
    { "month": 1, "day": 1, "title": "آغاز سال هجری قمری" },
    { "month": 1, "day": 9, "title": "تاسوعای حسینی" },
    { "month": 1, "day": 10, "title": "عاشورای حسینی" },
    { "month": 1, "day": 11, "title": "روز تجلیل از اسرا و مفقودان" },
    { "month": 1, "day": 12, "title": "شهادت امام زین‌العابدین (ع) (۹۵ ه‍.ق)" },
    { "month": 1, "day": 25, "title": "شهادت امام زین‌العابدین (ع) (۹۵ ه‍.ق) به روایتی" },
    { "month": 2, "day": 7, "title": "شهادت امام حسن مجتبی (ع) (۵۰ ه‍.ق) (به روایتی) – روز بزرگداشت سلمان فارسی" },
    { "month": 2, "day": 20, "title": "اربعین حسینی" },
    { "month": 2, "day": 27, "title": "روز وقف" },
    { "month": 2, "day": 28, "title": "رحلت حضرت رسول اکرم (ص) (۱۱ ه‍.ق) – شهادت امام حسن مجتبی (ع) (۵۰ ه‍.ق)" },
    { "month": 2, "day": 30, "title": "شهادت امام رضا (ع) (۲۰۳ ه‍.ق)" },
    { "month": 3, "day": 1, "title": "هجرت رسول اکرم (ص) از مکه به مدینه" },
    { "month": 3, "day": 8, "title": "شهادت امام حسن عسگری (ع) (۲۶۰ ه‍.ق)" },
    { "month": 3, "day": 12, "title": "ولادت حضرت رسول اکرم(ص) به روایت اهل سنت (۵۳ سال قبل از هجرت) - آغاز هفتهٔ وحدت" },
    { "month": 3, "day": 17, "title": "ولادت حضرت رسول اکرم (ص) (۵۳ سال قبل از هجرت) و روز اخلاق و مهرورزی – ولادت امام جعفر صادق (ع) مؤسس مذهب جعفری (۸۳ ه‍.ق)" },
    { "month": 4, "day": 8, "title": "ولادت امام حسن عسگری (ع) (۲۳۲ ه‍.ق)" },
    { "month": 4, "day": 10, "title": "وفات حضرت معصومه (س) (۲۰۱ ه‍.ق)" },
    { "month": 5, "day": 5, "title": "ولادت حضرت زینب (س) (۵ ه‍.ق) و روز پرستار" },
    { "month": 5, "day": 13, "title": "شهادت حضرت فاطمهٔ زهرا (س) (۱۱ ه‍.ق) به روایتی" },
    { "month": 6, "day": 3, "title": "شهادت حضرت فاطمهٔ زهرا (س) (۱۱ ه‍.ق)" },
    { "month": 6, "day": 13, "title": "سالروز وفات حضرت ام‌البنین (س) - روز تکریم مادران و همسران شهدا" },
    { "month": 6, "day": 20, "title": "ولادت حضرت فاطمهٔ زهرا (س) (سال هشتم قبل از هجرت) و روز زن – تولد امام خمینی(ره) رهبر کبیر انقلاب اسلامی (۱۳۲۰ ه‍.ق)" },
    { "month": 7, "day": 1, "title": "ولادت امام محمد باقر (ع) (۵۷ ه‍.ق)" },
    { "month": 7, "day": 3, "title": "شهادت امام علی النقی الهادی (ع) (۲۵۴ ه‍.ق)" },
    { "month": 7, "day": 10, "title": "ولادت امام محمد تقی (ع) (۱۹۵ ه‍.ق)" },
    { "month": 7, "day": 13, "title": "ولادت حضرت امام علی (ع) (۲۳ سال قبل از هجرت) – آغاز ایام‌البیض (اعتکاف)" },
    { "month": 7, "day": 15, "title": "وفات حضرت زینب (س) (۶۲ ه‍.ق) – تغییر قبلهٔ مسلمین از از بیت‌المقدس به مکهٔ معظمه (۲ ه‍.ق)" },
    { "month": 7, "day": 25, "title": "شهادت امام موسی کاظم (ع) (۱۸۳ ه‍.ق)" },
    { "month": 7, "day": 27, "title": "مبعث حضرت رسول اکرم (ص) (۱۳ سال قبل از هجرت)" },
    { "month": 8, "day": 3, "title": "ولادت امام حسین (ع) (۴ ه‍.ق) و روز پاسدار" },
    { "month": 8, "day": 4, "title": "ولادت حضرت ابوالفضل العباس (ع) (۲۶ ه‍.ق) و روز جانباز" },
    { "month": 8, "day": 5, "title": "ولادت امام زین‌العابدین (ع) (۳۸ ه‍.ق)" },
    { "month": 8, "day": 11, "title": "ولادت حضرت علی اکبر (ع) (۳۳ ه‍.ق) و روز جوان" },
    { "month": 8, "day": 15, "title": "ولادت حضرت قائم (عج) (۲۵۵ ه‍.ق) و روز جهانی مستضعفان" },
    { "month": 9, "day": 10, "title": "وفات حضرت خدیجه (س) (۳ سال قبل از هجرت)" },
    { "month": 9, "day": 15, "title": "ولادت امام حسن مجتبی (ع) (۳ ه‍.ق) و روز اکرام" },
    { "month": 9, "day": 18, "title": "شب قدر" },
    { "month": 9, "day": 19, "title": "ضربت خوردن حضرت علی (ع) (۵۴۰ ه‍.ق)" },
    { "month": 9, "day": 20, "title": "شب قدر" },
    { "month": 9, "day": 21, "title": "شهادت حضرت علی (ع) (۵۴۰ ه‍.ق)" },
    { "month": 9, "day": 22, "title": "شب قدر" },
    { "month": 10, "day": 1, "title": "عید سعید فطر" },
    { "month": 10, "day": 17, "title": "روز فرهنگ پهلوانی و ورزش زورخانه‌ای" },
    { "month": 10, "day": 25, "title": "شهادت امام جعفر صادق (ع) (۱۴۸ ه‍.ق)" },
    { "month": 11, "day": 1, "title": "ولادت حضرت معصومه (س) (۱۷۳ ه‍.ق) و روز دختران" },
    { "month": 11, "day": 5, "title": "روز تجلیل از امام‌زادگان و بقاع متبرکه" },
    { "month": 11, "day": 6, "title": "روز بزرگداشت حضرت احمدبن‌موسی شاهچراغ (ع)" },
    { "month": 11, "day": 11, "title": "ولادت امام رضا (ع) (۱۴۸ ه‍.ق)" },
    { "month": 11, "day": 30, "title": "شهادت امام محمد تقی (ع) (۲۲۰ ه‍.ق)" },
    { "month": 12, "day": 1, "title": "سالروز ازدواج حضرت علی (ع) و حضرت فاطمه (س) (۲ ه‍.ق) – روز ازدواج" },
    { "month": 12, "day": 6, "title": "شهادت مظلومانه زائران خانهٔ خدا به دستور آمریکا به دست مأموران آل سعود (۱۳۶۶ ه‍.ش برابر با ۶ ذی‌الحجه ۱۴۰۷ ه‍.ق)" },
    { "month": 12, "day": 7, "title": "شهادت امام محمد باقر (ع) (۱۱۴ ه‍.ق)" },
    { "month": 12, "day": 9, "title": "روز عرفه (روز نیایش)" },
    { "month": 12, "day": 10, "title": "عید سعید قربان (عید الاضحی)" },
    { "month": 12, "day": 15, "title": "ولادت امام علی النقی الهادی (ع) (۲۱۲ ه‍.ق)" },
    { "month": 12, "day": 18, "title": "عید سعید غدیر خم (۱۰ ه‍.ق)" },
    { "month": 12, "day": 20, "title": "ولادت امام موسی کاظم (ع) (۱۲۸ ه‍.ق)" },
    { "month": 12, "day": 24, "title": "روز مباهلهٔ پیامبر اسلام (ص) (۱۰ ه‍.ق)" },
    { "month": 12, "day": 25, "title": "روز خانواده و تکریم بازنشستگان" },

    { "month": 2, "day": 3, "title": "ولادت امام محمد باقر (ع) (۵۷ ﻫ.ق) به روایتی" },
    { "month": 3, "day": 12, "title": "آغاز واجب شدن نماز، ورود پیامبر به مدینه" },
    { "month": 3, "day": 15, "title": "بنای مسجد قبا (اولین مسجد در اسلام)" },
    { "month": 3, "day": 16, "title": "ورود اهل بیت اما حسین (ع) به شام" },
    { "month": 3, "day": 17, "title": "بنای مسجدالنبی در مدینه" },
    { "month": 3, "day": 23, "title": "ورود حضرت معصومه (س) به قم" },
    { "month": 3, "day": 26, "title": "صلح امام حسن (ع)" },
    { "month": 4, "day": 3, "title": "سفر اما حسن (ع) به جرجان" },
    { "month": 4, "day": 4, "title": "ولادت شاه عبدالعظیم حسنی (ع)" },
    { "month": 4, "day": 6, "title": "هلاکت هشام بن عبدالملک صادر کنندهٔ دستور شهادت امام باقر (ع)" },
    { "month": 4, "day": 8, "title": "شهادت حضرت فاطمهٔ زهرا (س) (۱۱ ﻫ.ق) به روایتی" },
    { "month": 5, "day": 10, "title": "وقوع جنگ جمل بین سپاهیان امام علی (ع) و ناکثین" },
    { "month": 5, "day": 27, "title": "وفات حضرت عبدالمطلب (ع)" },
    { "month": 6, "day": 4, "title": "هلاکت هارون‌الرشید قاتل اما کاظم (ع)" },
    { "month": 6, "day": 12, "title": "حرکت پیامبر به سمت خیبر" },
    { "month": 6, "day": 13, "title": "وفات ام‌البنین (س)" },
    { "month": 6, "day": 19, "title": "ازدواج حضرت عبداللّه (ع) و آمنه (س)" },
    { "month": 6, "day": 21, "title": "ولادت حضرت ام‌کلثوم (س)" },
    { "month": 7, "day": 9, "title": "ولادت حضرت علی اصغر (ع)" },
    { "month": 7, "day": 16, "title": "خروج فاطمه بنت اسد از کعبه" },
    { "month": 7, "day": 23, "title": "مجروح شدن اما حسن مجتبی(ع) در ستبتط مدائن، مسموم شدن امام موسی کاظم (ع) به دستور مأمون" },
    { "month": 7, "day": 24, "title": "فتح قلعهٔ خیبر توسط حضرت علی(ع)، بازگشت حعفر بن ابی‌طالب از حبشه" },
    { "month": 7, "day": 26, "title": "وفات حضرت ابوطالب (ع)" },
    { "month": 7, "day": 28, "title": "حرکت امام حسین (ع) از مدینه به مکه" },
    { "month": 7, "day": 30, "title": "هجرت مسلمانان به حبشه، غزوهٔ نخله" },
    { "month": 8, "day": 15, "title": "روز سربازان گمنام امام زمان (عج)" },
    { "month": 10, "day": 21, "title": "فتح اندلس به دست مسلمانان (۹۲ ه‍.ق)" },
    { "month": 11, "day": 5, "title": "روز بزرگداشت حضرت صالح بن موسی کاظم (ع)" }
  ]
}
